{
  "kind": "singleType",
  "collectionName": "blocks",
  "info": {
    "singularName": "block",
    "pluralName": "blocks",
    "displayName": "Blocks",
    "description": ""
  },
  "options": {
    "draftAndPublish": true
  },
  "pluginOptions": {
    "i18n": {
      "localized": true
    }
  },
  "attributes": {
    "text": {
      "type": "customField",
      "options": {
        "preset": "default"
      },
      "required": true,
      "customField": "plugin::ckeditor5.CKEditor"
    },
    "service": {
      "type": "component",
      "repeatable": true,
      "component": "services.services",
      "pluginOptions": {
        "i18n": {
          "localized": true
        }
      }
    },
    "order": {
      "type": "component",
      "repeatable": false,
      "component": "order.order",
      "required": true,
      "pluginOptions": {
        "i18n": {
          "localized": true
        }
      }
    }
  }
}
